molml/__init__.py
molml/atom.py
molml/base.py
molml/constants.py
molml/crystal.py
molml/features.py
molml/io.py
molml/kernel.py
molml/molecule.py
molml/utils.py
molml-0.8.0.dist-info/DESCRIPTION.rst
molml-0.8.0.dist-info/METADATA
molml-0.8.0.dist-info/RECORD
molml-0.8.0.dist-info/WHEEL
molml-0.8.0.dist-info/metadata.json
molml-0.8.0.dist-info/top_level.txt
